mainstay/__init__.py
mainstay/_base_client.py
mainstay/_client.py
mainstay/_compat.py
mainstay/_constants.py
mainstay/_exceptions.py
mainstay/_files.py
mainstay/_models.py
mainstay/_qs.py
mainstay/_resource.py
mainstay/_response.py
mainstay/_streaming.py
mainstay/_types.py
mainstay/_version.py
mainstay/py.typed
mainstay/_utils/__init__.py
mainstay/_utils/_logs.py
mainstay/_utils/_proxy.py
mainstay/_utils/_reflection.py
mainstay/_utils/_resources_proxy.py
mainstay/_utils/_streams.py
mainstay/_utils/_sync.py
mainstay/_utils/_transform.py
mainstay/_utils/_typing.py
mainstay/_utils/_utils.py
mainstay/lib/.keep
mainstay/resources/__init__.py
mainstay/resources/data/__init__.py
mainstay/resources/data/crime_data.py
mainstay/resources/data/data.py
mainstay/resources/data/property_details.py
mainstay/resources/data/property_values.py
mainstay/resources/data/rent_estimates.py
mainstay/resources/data/rental_comps.py
mainstay/resources/data/school_ratings.py
mainstay/types/__init__.py
mainstay/types/data/__init__.py
mainstay/types/data/crime_data_fetch_params.py
mainstay/types/data/crime_data_response.py
mainstay/types/data/property_details_fetch_params.py
mainstay/types/data/property_details_response.py
mainstay/types/data/property_values_fetch_params.py
mainstay/types/data/property_values_response.py
mainstay/types/data/rent_estimates_fetch_params.py
mainstay/types/data/rent_estimates_response.py
mainstay/types/data/rental_comps_fetch_params.py
mainstay/types/data/rental_comps_response.py
mainstay/types/data/school_ratings_fetch_params.py
mainstay/types/data/school_ratings_response.py
mainstay-0.1.0a26.dist-info/METADATA
mainstay-0.1.0a26.dist-info/WHEEL
mainstay-0.1.0a26.dist-info/licenses/LICENSE
mainstay-0.1.0a26.dist-info/RECORD
